udomratibaapi/__init__.py
udomratibaapi/ratiba.py
udomratibaapi/utils.py
udomratibaapi-0.0.1.dist-info/LICENSE
udomratibaapi-0.0.1.dist-info/METADATA
udomratibaapi-0.0.1.dist-info/WHEEL
udomratibaapi-0.0.1.dist-info/top_level.txt
udomratibaapi-0.0.1.dist-info/RECORD
