Metadata-Version: 2.1
Name: udomratibaapi
Version: 0.0.1
Summary: Fetch data from the UDOM ratiba website in a clean JSON format
Home-page: https://github.com/vincent-laizer/UDOM-Ratiba-API
Author: Vincent Laizer
Author-email: <laizercorp@gmail.com>
License: UNKNOWN
Keywords: udom,ratiba,api,python,udom api,ratiba api,udom python
Platform: UNKNOWN
Classifier: Development Status :: 4 - Beta
Classifier: Intended Audience :: Developers
Classifier: Programming Language :: Python :: 3
Classifier: Operating System :: Unix
Classifier: Operating System :: MacOS :: MacOS X
Classifier: Operating System :: Microsoft :: Windows
License-File: LICENSE
